{"2024-03-05-2024-03-05": {"VEN - Medios adversos- TIK TOK": [{"valor": 16, "palabra": "venezuela"}, {"valor": 11, "palabra": "nuestro"}, {"valor": 9, "palabra": "disponible"}, {"valor": 8, "palabra": "youtube"}, {"valor": 8, "palabra": "corina"}, {"valor": 7, "palabra": "presidente"}, {"valor": 6, "palabra": "noticias"}, {"valor": 6, "palabra": "nuestras"}, {"valor": 6, "palabra": "impacto"}, {"valor": 5, "palabra": "síguenos"}, {"valor": 4, "palabra": "película"}, {"valor": 4, "palabra": "completa"}, {"valor": 4, "palabra": "sociales"}, {"valor": 4, "palabra": "destacadas"}, {"valor": 4, "palabra": "nuestra"}, {"valor": 4, "palabra": "locura"}, {"valor": 3, "palabra": "presidenciales"}, {"valor": 3, "palabra": "pierdas"}, {"valor": 3, "palabra": "comunidad"}, {"valor": 3, "palabra": "nacional"}, {"valor": 3, "palabra": "plataformas"}, {"valor": 3, "palabra": "ondemand"}, {"valor": 3, "palabra": "elecciones"}, {"valor": 3, "palabra": "porque"}, {"valor": 3, "palabra": "sanciones"}, {"valor": 3, "palabra": "chavismo"}, {"valor": 2, "palabra": "cuando"}, {"valor": 2, "palabra": "verdad"}, {"valor": 2, "palabra": "emisión"}, {"valor": 2, "palabra": "noticiero"}, {"valor": 2, "palabra": "historias"}, {"valor": 2, "palabra": "películas"}, {"valor": 2, "palabra": "primera"}, {"valor": 2, "palabra": "reciente"}, {"valor": 2, "palabra": "entrega"}, {"valor": 2, "palabra": "machado"}, {"valor": 2, "palabra": "maduro"}, {"valor": 2, "palabra": "electoral"}, {"valor": 2, "palabra": "apertura"}, {"valor": 2, "palabra": "fallas"}], "VEN - Medios afines - TIK TOK": [{"valor": 47, "palabra": "guerra"}, {"valor": 30, "palabra": "francia"}, {"valor": 30, "palabra": "ucrania"}, {"valor": 29, "palabra": "presidente"}, {"valor": 26, "palabra": "siempre"}, {"valor": 25, "palabra": "cuando"}, {"valor": 24, "palabra": "porque"}, {"valor": 24, "palabra": "quieren"}, {"valor": 23, "palabra": "políticos"}, {"valor": 20, "palabra": "alemania"}, {"valor": 19, "palabra": "tienen"}, {"valor": 18, "palabra": "verdad"}, {"valor": 17, "palabra": "venezuela"}, {"valor": 17, "palabra": "mundial"}, {"valor": 17, "palabra": "importa"}, {"valor": 16, "palabra": "chávez"}, {"valor": 16, "palabra": "quiere"}, {"valor": 16, "palabra": "unidos"}, {"valor": 16, "palabra": "gracias"}, {"valor": 16, "palabra": "gobierno"}, {"valor": 15, "palabra": "méxico"}, {"valor": 15, "palabra": "dinero"}, {"valor": 15, "palabra": "entonces"}, {"valor": 15, "palabra": "estados"}, {"valor": 14, "palabra": "noticias"}, {"valor": 14, "palabra": "minería"}, {"valor": 14, "palabra": "países"}, {"valor": 14, "palabra": "corruptos"}, {"valor": 14, "palabra": "inolvidable"}, {"valor": 13, "palabra": "libertad"}, {"valor": 12, "palabra": "jajaja"}, {"valor": 12, "palabra": "mentira"}, {"valor": 11, "palabra": "nuestro"}, {"valor": 11, "palabra": "contra"}, {"valor": 11, "palabra": "américa"}, {"valor": 10, "palabra": "patria"}, {"valor": 10, "palabra": "pueblo"}, {"valor": 10, "palabra": "millones"}, {"valor": 10, "palabra": "energía"}, {"valor": 10, "palabra": "muchos"}], "VEN - Nicolás Maduro - TIK TOK": [{"valor": 158, "palabra": "presidente"}, {"valor": 56, "palabra": "maduro"}, {"valor": 43, "palabra": "corina"}, {"valor": 40, "palabra": "pueblo"}, {"valor": 37, "palabra": "venezuela"}, {"valor": 30, "palabra": "montaje"}, {"valor": 22, "palabra": "necesito"}, {"valor": 18, "palabra": "bendiga"}, {"valor": 17, "palabra": "saludos"}, {"valor": 14, "palabra": "machado"}, {"valor": 14, "palabra": "siempre"}, {"valor": 13, "palabra": "porque"}, {"valor": 13, "palabra": "cuando"}, {"valor": 12, "palabra": "jajaja"}, {"valor": 11, "palabra": "publicidad"}, {"valor": 11, "palabra": "vivienda"}, {"valor": 11, "palabra": "bendiciones"}, {"valor": 11, "palabra": "tienen"}, {"valor": 11, "palabra": "nicolás"}, {"valor": 10, "palabra": "estamos"}, {"valor": 10, "palabra": "trabajo"}, {"valor": 10, "palabra": "verdad"}, {"valor": 10, "palabra": "chávez"}, {"valor": 9, "palabra": "quieren"}, {"valor": 9, "palabra": "hambre"}, {"valor": 9, "palabra": "dinero"}, {"valor": 9, "palabra": "familia"}, {"valor": 9, "palabra": "miseria"}, {"valor": 9, "palabra": "gobierno"}, {"valor": 8, "palabra": "teques"}, {"valor": 8, "palabra": "barinas"}, {"valor": 8, "palabra": "necesitamos"}, {"valor": 8, "palabra": "venceremos"}, {"valor": 8, "palabra": "buenas"}, {"valor": 8, "palabra": "elecciones"}, {"valor": 8, "palabra": "muchos"}, {"valor": 8, "palabra": "trabajar"}, {"valor": 8, "palabra": "mentira"}, {"valor": 8, "palabra": "comandante"}, {"valor": 8, "palabra": "patria"}]}, "2024-03-06-2024-03-06": {"VEN - Medios adversos- TIK TOK": [{"valor": 45, "palabra": "corina"}, {"valor": 37, "palabra": "venezuela"}, {"valor": 26, "palabra": "presidente"}, {"valor": 22, "palabra": "pueblo"}, {"valor": 18, "palabra": "machado"}, {"valor": 13, "palabra": "porque"}, {"valor": 13, "palabra": "supuesto"}, {"valor": 12, "palabra": "nuestro"}, {"valor": 11, "palabra": "nuestra"}, {"valor": 11, "palabra": "elecciones"}, {"valor": 10, "palabra": "respaldo"}, {"valor": 10, "palabra": "cuando"}, {"valor": 9, "palabra": "disponible"}, {"valor": 9, "palabra": "apollo"}, {"valor": 9, "palabra": "siiiiii"}, {"valor": 8, "palabra": "tienen"}, {"valor": 8, "palabra": "maduro"}, {"valor": 8, "palabra": "youtube"}, {"valor": 8, "palabra": "quiere"}, {"valor": 8, "palabra": "jajajaja"}, {"valor": 7, "palabra": "impacto"}, {"valor": 7, "palabra": "dispuesto"}, {"valor": 7, "palabra": "inscribir"}, {"valor": 7, "palabra": "sanciones"}, {"valor": 7, "palabra": "acuerdo"}, {"valor": 6, "palabra": "electoral"}, {"valor": 6, "palabra": "venezolanos"}, {"valor": 6, "palabra": "persona"}, {"valor": 6, "palabra": "estamos"}, {"valor": 6, "palabra": "caraotas"}, {"valor": 5, "palabra": "gobierno"}, {"valor": 5, "palabra": "nuestras"}, {"valor": 5, "palabra": "presidenciales"}, {"valor": 5, "palabra": "venezolano"}, {"valor": 5, "palabra": "síguenos"}, {"valor": 5, "palabra": "pidiendo"}, {"valor": 5, "palabra": "después"}, {"valor": 5, "palabra": "inscribirse"}, {"valor": 5, "palabra": "lorenzo"}, {"valor": 5, "palabra": "apoyamos"}], "VEN - Medios afines - TIK TOK": [{"valor": 102, "palabra": "presidente"}, {"valor": 53, "palabra": "siempre"}, {"valor": 47, "palabra": "gracias"}, {"valor": 47, "palabra": "ucrania"}, {"valor": 39, "palabra": "venezuela"}, {"valor": 39, "palabra": "grande"}, {"valor": 37, "palabra": "tienen"}, {"valor": 35, "palabra": "porque"}, {"valor": 34, "palabra": "nuestro"}, {"valor": 34, "palabra": "cuando"}, {"valor": 31, "palabra": "chávez"}, {"valor": 31, "palabra": "chicos"}, {"valor": 30, "palabra": "excelente"}, {"valor": 30, "palabra": "patria"}, {"valor": 29, "palabra": "vladimir"}, {"valor": 28, "palabra": "pueblo"}, {"valor": 26, "palabra": "gobierno"}, {"valor": 26, "palabra": "hambre"}, {"valor": 25, "palabra": "jajaja"}, {"valor": 23, "palabra": "contra"}, {"valor": 22, "palabra": "mundial"}, {"valor": 22, "palabra": "políticos"}, {"valor": 21, "palabra": "noticias"}, {"valor": 21, "palabra": "chavez"}, {"valor": 21, "palabra": "guerra"}, {"valor": 21, "palabra": "energía"}, {"valor": 19, "palabra": "francia"}, {"valor": 19, "palabra": "dinero"}, {"valor": 18, "palabra": "minería"}, {"valor": 18, "palabra": "saludos"}, {"valor": 18, "palabra": "bendiga"}, {"valor": 17, "palabra": "palabras"}, {"valor": 17, "palabra": "estado"}, {"valor": 17, "palabra": "jóvenes"}, {"valor": 17, "palabra": "comandante"}, {"valor": 17, "palabra": "estados"}, {"valor": 16, "palabra": "argentina"}, {"valor": 16, "palabra": "hombre"}, {"valor": 16, "palabra": "asesino"}, {"valor": 15, "palabra": "estamos"}], "VEN - Nicolás Maduro - TIK TOK": [{"valor": 133, "palabra": "presidente"}, {"valor": 70, "palabra": "maduro"}, {"valor": 50, "palabra": "corina"}, {"valor": 29, "palabra": "pueblo"}, {"valor": 27, "palabra": "venezuela"}, {"valor": 18, "palabra": "jajaja"}, {"valor": 14, "palabra": "montaje"}, {"valor": 14, "palabra": "bendiga"}, {"valor": 14, "palabra": "estado"}, {"valor": 14, "palabra": "machado"}, {"valor": 13, "palabra": "nicolas"}, {"valor": 13, "palabra": "cuando"}, {"valor": 12, "palabra": "quiere"}, {"valor": 10, "palabra": "saludos"}, {"valor": 10, "palabra": "nicolás"}, {"valor": 10, "palabra": "necesito"}, {"valor": 9, "palabra": "venceremos"}, {"valor": 9, "palabra": "verdad"}, {"valor": 9, "palabra": "siempre"}, {"valor": 9, "palabra": "nuestro"}, {"valor": 9, "palabra": "vivienda"}, {"valor": 8, "palabra": "porque"}, {"valor": 8, "palabra": "libertad"}, {"valor": 8, "palabra": "bendiciones"}, {"valor": 7, "palabra": "venezolanos"}, {"valor": 7, "palabra": "precidente"}, {"valor": 7, "palabra": "familia"}, {"valor": 6, "palabra": "palante"}, {"valor": 6, "palabra": "personas"}, {"valor": 6, "palabra": "muchas"}, {"valor": 6, "palabra": "saludo"}, {"valor": 6, "palabra": "quiero"}, {"valor": 6, "palabra": "cuenta"}, {"valor": 6, "palabra": "mentira"}, {"valor": 6, "palabra": "hambre"}, {"valor": 6, "palabra": "municipio"}, {"valor": 5, "palabra": "patria"}, {"valor": 5, "palabra": "miranda"}, {"valor": 5, "palabra": "gobierno"}, {"valor": 5, "palabra": "comandante"}]}, "2024-03-07-2024-03-07": {"VEN - Medios adversos- TIK TOK": [{"valor": 36, "palabra": "corina"}, {"valor": 26, "palabra": "venezuela"}, {"valor": 21, "palabra": "elecciones"}, {"valor": 17, "palabra": "nuestro"}, {"valor": 17, "palabra": "maduro"}, {"valor": 15, "palabra": "gobierno"}, {"valor": 14, "palabra": "presidente"}, {"valor": 13, "palabra": "porque"}, {"valor": 9, "palabra": "disponible"}, {"valor": 9, "palabra": "youtube"}, {"valor": 9, "palabra": "pueblo"}, {"valor": 8, "palabra": "presidenta"}, {"valor": 7, "palabra": "cuando"}, {"valor": 6, "palabra": "presidenciales"}, {"valor": 6, "palabra": "nuestra"}, {"valor": 6, "palabra": "impacto"}, {"valor": 6, "palabra": "verdad"}, {"valor": 6, "palabra": "siempre"}, {"valor": 5, "palabra": "comunidad"}, {"valor": 5, "palabra": "síguenos"}, {"valor": 5, "palabra": "oposición"}, {"valor": 5, "palabra": "candidato"}, {"valor": 5, "palabra": "machado"}, {"valor": 5, "palabra": "jajajaja"}, {"valor": 4, "palabra": "nuestras"}, {"valor": 4, "palabra": "destacadas"}, {"valor": 4, "palabra": "venezolanos"}, {"valor": 4, "palabra": "pregunta"}, {"valor": 4, "palabra": "campaña"}, {"valor": 4, "palabra": "carajo"}, {"valor": 4, "palabra": "quiere"}, {"valor": 4, "palabra": "queremos"}, {"valor": 4, "palabra": "inhabilitada"}, {"valor": 3, "palabra": "internacional"}, {"valor": 3, "palabra": "noticias"}, {"valor": 3, "palabra": "pierdas"}, {"valor": 3, "palabra": "emisión"}, {"valor": 3, "palabra": "completa"}, {"valor": 3, "palabra": "noticiero"}, {"valor": 3, "palabra": "sociales"}], "VEN - Medios afines - TIK TOK": [{"valor": 74, "palabra": "presidente"}, {"valor": 37, "palabra": "grande"}, {"valor": 32, "palabra": "mundial"}, {"valor": 29, "palabra": "guerra"}, {"valor": 29, "palabra": "siempre"}, {"valor": 26, "palabra": "vladimir"}, {"valor": 22, "palabra": "porque"}, {"valor": 21, "palabra": "hombre"}, {"valor": 18, "palabra": "pueblo"}, {"valor": 18, "palabra": "excelente"}, {"valor": 18, "palabra": "bendiga"}, {"valor": 17, "palabra": "humanidad"}, {"valor": 16, "palabra": "ucrania"}, {"valor": 15, "palabra": "venezuela"}, {"valor": 14, "palabra": "nuestro"}, {"valor": 14, "palabra": "gracias"}, {"valor": 14, "palabra": "saludos"}, {"valor": 14, "palabra": "cuando"}, {"valor": 12, "palabra": "maduro"}, {"valor": 12, "palabra": "humano"}, {"valor": 12, "palabra": "libertad"}, {"valor": 12, "palabra": "hambre"}, {"valor": 12, "palabra": "caballero"}, {"valor": 11, "palabra": "gobierno"}, {"valor": 11, "palabra": "patria"}, {"valor": 11, "palabra": "quiero"}, {"valor": 10, "palabra": "parece"}, {"valor": 10, "palabra": "respeto"}, {"valor": 10, "palabra": "méxico"}, {"valor": 10, "palabra": "también"}, {"valor": 10, "palabra": "quiere"}, {"valor": 10, "palabra": "responsabilidad"}, {"valor": 9, "palabra": "estado"}, {"valor": 9, "palabra": "argentina"}, {"valor": 9, "palabra": "tienen"}, {"valor": 9, "palabra": "medios"}, {"valor": 9, "palabra": "russia"}, {"valor": 9, "palabra": "planeta"}, {"valor": 9, "palabra": "muchos"}, {"valor": 9, "palabra": "fuerza"}], "VEN - Nicolás Maduro - TIK TOK": [{"valor": 171, "palabra": "presidente"}, {"valor": 84, "palabra": "maduro"}, {"valor": 52, "palabra": "corina"}, {"valor": 43, "palabra": "venezuela"}, {"valor": 34, "palabra": "pueblo"}, {"valor": 22, "palabra": "saludos"}, {"valor": 21, "palabra": "bendiga"}, {"valor": 21, "palabra": "estado"}, {"valor": 21, "palabra": "tienen"}, {"valor": 18, "palabra": "bendiciones"}, {"valor": 18, "palabra": "venceremos"}, {"valor": 18, "palabra": "gobierno"}, {"valor": 17, "palabra": "cuando"}, {"valor": 17, "palabra": "necesito"}, {"valor": 15, "palabra": "afuera"}, {"valor": 15, "palabra": "elecciones"}, {"valor": 15, "palabra": "nicolás"}, {"valor": 15, "palabra": "siempre"}, {"valor": 15, "palabra": "porque"}, {"valor": 15, "palabra": "quiero"}, {"valor": 14, "palabra": "hambre"}, {"valor": 12, "palabra": "tienes"}, {"valor": 12, "palabra": "municipio"}, {"valor": 12, "palabra": "estamos"}, {"valor": 12, "palabra": "machado"}, {"valor": 11, "palabra": "chavista"}, {"valor": 10, "palabra": "carajo"}, {"valor": 10, "palabra": "patria"}, {"valor": 9, "palabra": "quiere"}, {"valor": 9, "palabra": "vivienda"}, {"valor": 9, "palabra": "nicolas"}, {"valor": 9, "palabra": "nuestro"}, {"valor": 8, "palabra": "trampa"}, {"valor": 8, "palabra": "chávez"}, {"valor": 8, "palabra": "oposición"}, {"valor": 8, "palabra": "palante"}, {"valor": 8, "palabra": "nosotros"}, {"valor": 8, "palabra": "precidente"}, {"valor": 8, "palabra": "familia"}, {"valor": 8, "palabra": "obligados"}]}, "2024-03-08-2024-03-08": {"VEN - Medios adversos- TIK TOK": [{"valor": 72, "palabra": "corina"}, {"valor": 62, "palabra": "venezuela"}, {"valor": 56, "palabra": "elecciones"}, {"valor": 47, "palabra": "presidente"}, {"valor": 30, "palabra": "pueblo"}, {"valor": 29, "palabra": "porque"}, {"valor": 27, "palabra": "machado"}, {"valor": 27, "palabra": "maduro"}, {"valor": 20, "palabra": "españa"}, {"valor": 17, "palabra": "gobierno"}, {"valor": 16, "palabra": "cuando"}, {"valor": 15, "palabra": "nuestro"}, {"valor": 13, "palabra": "siempre"}, {"valor": 12, "palabra": "tienen"}, {"valor": 12, "palabra": "quiere"}, {"valor": 12, "palabra": "inhabilitada"}, {"valor": 11, "palabra": "policías"}, {"valor": 10, "palabra": "youtube"}, {"valor": 10, "palabra": "queremos"}, {"valor": 9, "palabra": "participar"}, {"valor": 9, "palabra": "régimen"}, {"valor": 9, "palabra": "elegir"}, {"valor": 8, "palabra": "disponible"}, {"valor": 8, "palabra": "acuerdo"}, {"valor": 8, "palabra": "oposición"}, {"valor": 8, "palabra": "presidenta"}, {"valor": 8, "palabra": "tiempo"}, {"valor": 8, "palabra": "manuales"}, {"valor": 8, "palabra": "dictadura"}, {"valor": 7, "palabra": "unidos"}, {"valor": 7, "palabra": "policía"}, {"valor": 7, "palabra": "entonces"}, {"valor": 7, "palabra": "venezolanos"}, {"valor": 7, "palabra": "inscribir"}, {"valor": 6, "palabra": "estamos"}, {"valor": 6, "palabra": "estado"}, {"valor": 6, "palabra": "impacto"}, {"valor": 6, "palabra": "primarias"}, {"valor": 6, "palabra": "trampa"}, {"valor": 6, "palabra": "patria"}], "VEN - Medios afines - TIK TOK": [{"valor": 68, "palabra": "presidente"}, {"valor": 62, "palabra": "toriyama"}, {"valor": 50, "palabra": "gracias"}, {"valor": 32, "palabra": "siempre"}, {"valor": 28, "palabra": "comida"}, {"valor": 25, "palabra": "guerra"}, {"valor": 25, "palabra": "infancia"}, {"valor": 24, "palabra": "cuando"}, {"valor": 23, "palabra": "grande"}, {"valor": 22, "palabra": "porque"}, {"valor": 19, "palabra": "ucrania"}, {"valor": 18, "palabra": "nuestro"}, {"valor": 17, "palabra": "unidos"}, {"valor": 17, "palabra": "jajaja"}, {"valor": 17, "palabra": "dragón"}, {"valor": 16, "palabra": "alimentos"}, {"valor": 15, "palabra": "maestro"}, {"valor": 14, "palabra": "dragon"}, {"valor": 14, "palabra": "tienen"}, {"valor": 14, "palabra": "mundial"}, {"valor": 14, "palabra": "descansa"}, {"valor": 13, "palabra": "estados"}, {"valor": 13, "palabra": "donald"}, {"valor": 12, "palabra": "estado"}, {"valor": 12, "palabra": "libertad"}, {"valor": 11, "palabra": "victoria"}, {"valor": 11, "palabra": "escasez"}, {"valor": 11, "palabra": "personas"}, {"valor": 11, "palabra": "verdad"}, {"valor": 11, "palabra": "democracia"}, {"valor": 11, "palabra": "vladimir"}, {"valor": 11, "palabra": "también"}, {"valor": 11, "palabra": "excelente"}, {"valor": 10, "palabra": "jajajaja"}, {"valor": 10, "palabra": "gobierno"}, {"valor": 9, "palabra": "venezuela"}, {"valor": 9, "palabra": "persona"}, {"valor": 9, "palabra": "quieren"}, {"valor": 9, "palabra": "contra"}, {"valor": 9, "palabra": "noticia"}], "VEN - Nicolás Maduro - TIK TOK": [{"valor": 329, "palabra": "presidente"}, {"valor": 257, "palabra": "maduro"}, {"valor": 173, "palabra": "corina"}, {"valor": 96, "palabra": "venezuela"}, {"valor": 88, "palabra": "pueblo"}, {"valor": 61, "palabra": "necesito"}, {"valor": 55, "palabra": "bendiga"}, {"valor": 48, "palabra": "machado"}, {"valor": 43, "palabra": "porque"}, {"valor": 40, "palabra": "siempre"}, {"valor": 36, "palabra": "quiere"}, {"valor": 36, "palabra": "estado"}, {"valor": 36, "palabra": "tienen"}, {"valor": 35, "palabra": "cuando"}, {"valor": 33, "palabra": "saludos"}, {"valor": 31, "palabra": "gobierno"}, {"valor": 30, "palabra": "jajaja"}, {"valor": 30, "palabra": "bendiciones"}, {"valor": 28, "palabra": "presidenta"}, {"valor": 27, "palabra": "nicolás"}, {"valor": 25, "palabra": "verdad"}, {"valor": 24, "palabra": "personas"}, {"valor": 24, "palabra": "estamos"}, {"valor": 23, "palabra": "vivienda"}, {"valor": 22, "palabra": "tienes"}, {"valor": 21, "palabra": "gracias"}, {"valor": 21, "palabra": "quiero"}, {"valor": 21, "palabra": "jajajaja"}, {"valor": 20, "palabra": "trabajo"}, {"valor": 20, "palabra": "palante"}, {"valor": 19, "palabra": "venceremos"}, {"valor": 19, "palabra": "elecciones"}, {"valor": 18, "palabra": "nuestro"}, {"valor": 17, "palabra": "mujeres"}, {"valor": 17, "palabra": "sueldo"}, {"valor": 17, "palabra": "adelante"}, {"valor": 17, "palabra": "comandante"}, {"valor": 17, "palabra": "buenas"}, {"valor": 17, "palabra": "hambre"}, {"valor": 17, "palabra": "oposición"}]}, "2024-03-09-2024-03-09": {"VEN - Medios adversos- TIK TOK": [{"valor": 12, "palabra": "venezuela"}, {"valor": 12, "palabra": "corina"}, {"valor": 9, "palabra": "cuando"}, {"valor": 8, "palabra": "porque"}, {"valor": 7, "palabra": "tienen"}, {"valor": 7, "palabra": "elecciones"}, {"valor": 7, "palabra": "pueblo"}, {"valor": 7, "palabra": "policía"}, {"valor": 7, "palabra": "gobierno"}, {"valor": 6, "palabra": "maduro"}, {"valor": 6, "palabra": "presidente"}, {"valor": 5, "palabra": "venezolanos"}, {"valor": 5, "palabra": "destacadas"}, {"valor": 5, "palabra": "nuestra"}, {"valor": 5, "palabra": "cambio"}, {"valor": 4, "palabra": "noticias"}, {"valor": 4, "palabra": "sociales"}, {"valor": 4, "palabra": "comunidad"}, {"valor": 4, "palabra": "primarias"}, {"valor": 4, "palabra": "nombre"}, {"valor": 3, "palabra": "justicia"}, {"valor": 3, "palabra": "nuestro"}, {"valor": 3, "palabra": "ampliar"}, {"valor": 3, "palabra": "nuestras"}, {"valor": 3, "palabra": "historias"}, {"valor": 3, "palabra": "presidenciales"}, {"valor": 3, "palabra": "sustituto"}, {"valor": 3, "palabra": "después"}, {"valor": 3, "palabra": "machado"}, {"valor": 3, "palabra": "seguir"}, {"valor": 3, "palabra": "libres"}, {"valor": 3, "palabra": "crímenes"}, {"valor": 3, "palabra": "venezolano"}, {"valor": 3, "palabra": "difícil"}, {"valor": 3, "palabra": "funcionario"}, {"valor": 3, "palabra": "cualquier"}, {"valor": 3, "palabra": "mayoría"}, {"valor": 3, "palabra": "hablan"}, {"valor": 3, "palabra": "identificación"}, {"valor": 3, "palabra": "policia"}], "VEN - Medios afines - TIK TOK": [{"valor": 82, "palabra": "guerra"}, {"valor": 60, "palabra": "presidente"}, {"valor": 46, "palabra": "ucrania"}, {"valor": 36, "palabra": "comida"}, {"valor": 35, "palabra": "porque"}, {"valor": 29, "palabra": "alimentos"}, {"valor": 29, "palabra": "tienen"}, {"valor": 29, "palabra": "cuando"}, {"valor": 28, "palabra": "quiere"}, {"valor": 26, "palabra": "siempre"}, {"valor": 24, "palabra": "unidos"}, {"valor": 23, "palabra": "estados"}, {"valor": 22, "palabra": "jajaja"}, {"valor": 18, "palabra": "mundial"}, {"valor": 17, "palabra": "nuestro"}, {"valor": 17, "palabra": "gobierno"}, {"valor": 17, "palabra": "países"}, {"valor": 16, "palabra": "pueblo"}, {"valor": 16, "palabra": "jajajaja"}, {"valor": 15, "palabra": "venezuela"}, {"valor": 15, "palabra": "escasez"}, {"valor": 14, "palabra": "donald"}, {"valor": 14, "palabra": "guerras"}, {"valor": 14, "palabra": "libertad"}, {"valor": 14, "palabra": "nuclear"}, {"valor": 14, "palabra": "después"}, {"valor": 13, "palabra": "verdad"}, {"valor": 13, "palabra": "gracias"}, {"valor": 13, "palabra": "quieren"}, {"valor": 12, "palabra": "estamos"}, {"valor": 12, "palabra": "méxico"}, {"valor": 11, "palabra": "personas"}, {"valor": 11, "palabra": "discurso"}, {"valor": 11, "palabra": "haciendo"}, {"valor": 11, "palabra": "también"}, {"valor": 11, "palabra": "precios"}, {"valor": 11, "palabra": "corina"}, {"valor": 10, "palabra": "estado"}, {"valor": 10, "palabra": "nuestra"}, {"valor": 10, "palabra": "maduro"}], "VEN - Nicolás Maduro - TIK TOK": [{"valor": 280, "palabra": "presidente"}, {"valor": 124, "palabra": "corina"}, {"valor": 114, "palabra": "maduro"}, {"valor": 89, "palabra": "venezuela"}, {"valor": 64, "palabra": "pueblo"}, {"valor": 54, "palabra": "jajaja"}, {"valor": 47, "palabra": "bendiga"}, {"valor": 39, "palabra": "machado"}, {"valor": 36, "palabra": "siempre"}, {"valor": 34, "palabra": "bendiciones"}, {"valor": 34, "palabra": "cuando"}, {"valor": 32, "palabra": "necesito"}, {"valor": 31, "palabra": "saludos"}, {"valor": 30, "palabra": "porque"}, {"valor": 29, "palabra": "quiere"}, {"valor": 29, "palabra": "gobierno"}, {"valor": 29, "palabra": "estamos"}, {"valor": 27, "palabra": "gracias"}, {"valor": 26, "palabra": "nicolás"}, {"valor": 26, "palabra": "estado"}, {"valor": 23, "palabra": "sueldo"}, {"valor": 23, "palabra": "hambre"}, {"valor": 23, "palabra": "vivienda"}, {"valor": 23, "palabra": "guerrera"}, {"valor": 22, "palabra": "venceremos"}, {"valor": 21, "palabra": "mujeres"}, {"valor": 19, "palabra": "quiero"}, {"valor": 19, "palabra": "nuestro"}, {"valor": 18, "palabra": "miseria"}, {"valor": 18, "palabra": "presidenta"}, {"valor": 18, "palabra": "jajajaja"}, {"valor": 17, "palabra": "tienen"}, {"valor": 17, "palabra": "adelante"}, {"valor": 16, "palabra": "ustedes"}, {"valor": 16, "palabra": "personas"}, {"valor": 16, "palabra": "palante"}, {"valor": 14, "palabra": "ayúdeme"}, {"valor": 14, "palabra": "verdad"}, {"valor": 14, "palabra": "nicolas"}, {"valor": 14, "palabra": "buenas"}]}, "2024-03-10-2024-03-10": {"VEN - Medios adversos- TIK TOK": [{"valor": 13, "palabra": "venezuela"}, {"valor": 7, "palabra": "porque"}, {"valor": 7, "palabra": "sanciones"}, {"valor": 5, "palabra": "corina"}, {"valor": 5, "palabra": "pueblo"}, {"valor": 5, "palabra": "gobierno"}, {"valor": 4, "palabra": "importa"}, {"valor": 4, "palabra": "machado"}, {"valor": 3, "palabra": "venezolanos"}, {"valor": 3, "palabra": "nuestro"}, {"valor": 3, "palabra": "youtube"}, {"valor": 3, "palabra": "natalicio"}, {"valor": 3, "palabra": "pierdas"}, {"valor": 3, "palabra": "chávez"}, {"valor": 3, "palabra": "maduro"}, {"valor": 3, "palabra": "volver"}, {"valor": 3, "palabra": "tienen"}, {"valor": 3, "palabra": "libertad"}, {"valor": 2, "palabra": "conocer"}, {"valor": 2, "palabra": "historias"}, {"valor": 2, "palabra": "médico"}, {"valor": 2, "palabra": "profesionales"}, {"valor": 2, "palabra": "población"}, {"valor": 2, "palabra": "crisis"}, {"valor": 2, "palabra": "muchos"}, {"valor": 2, "palabra": "ningún"}, {"valor": 2, "palabra": "nuestra"}, {"valor": 2, "palabra": "elecciones"}, {"valor": 2, "palabra": "electoral"}, {"valor": 2, "palabra": "venezolano"}, {"valor": 2, "palabra": "garrido"}, {"valor": 2, "palabra": "tenemos"}, {"valor": 2, "palabra": "petróleo"}, {"valor": 2, "palabra": "presidente"}, {"valor": 2, "palabra": "opositores"}, {"valor": 2, "palabra": "bloqueo"}, {"valor": 2, "palabra": "instancia"}, {"valor": 2, "palabra": "cualquier"}, {"valor": 2, "palabra": "cuando"}, {"valor": 2, "palabra": "venceremos"}], "VEN - Medios afines - TIK TOK": [{"valor": 121, "palabra": "presidente"}, {"valor": 71, "palabra": "venezuela"}, {"valor": 67, "palabra": "realidad"}, {"valor": 61, "palabra": "película"}, {"valor": 56, "palabra": "verdad"}, {"valor": 43, "palabra": "maduro"}, {"valor": 43, "palabra": "necesito"}, {"valor": 40, "palabra": "cuando"}, {"valor": 32, "palabra": "siempre"}, {"valor": 28, "palabra": "guerra"}, {"valor": 28, "palabra": "netflix"}, {"valor": 24, "palabra": "porque"}, {"valor": 21, "palabra": "jajajaja"}, {"valor": 20, "palabra": "quieren"}, {"valor": 20, "palabra": "vivimos"}, {"valor": 17, "palabra": "pueblo"}, {"valor": 17, "palabra": "historia"}, {"valor": 17, "palabra": "gobierno"}, {"valor": 16, "palabra": "ucrania"}, {"valor": 16, "palabra": "unidos"}, {"valor": 16, "palabra": "jajaja"}, {"valor": 15, "palabra": "buenos"}, {"valor": 15, "palabra": "bendiga"}, {"valor": 15, "palabra": "corina"}, {"valor": 14, "palabra": "comida"}, {"valor": 14, "palabra": "trabajo"}, {"valor": 14, "palabra": "países"}, {"valor": 14, "palabra": "tienen"}, {"valor": 14, "palabra": "gracias"}, {"valor": 14, "palabra": "cuenta"}, {"valor": 13, "palabra": "mundial"}, {"valor": 13, "palabra": "estados"}, {"valor": 13, "palabra": "estado"}, {"valor": 12, "palabra": "ustedes"}, {"valor": 12, "palabra": "también"}, {"valor": 11, "palabra": "nuestro"}, {"valor": 11, "palabra": "quiero"}, {"valor": 11, "palabra": "muchos"}, {"valor": 11, "palabra": "precidente"}, {"valor": 11, "palabra": "películas"}], "VEN - Nicolás Maduro - TIK TOK": [{"valor": 60, "palabra": "presidente"}, {"valor": 34, "palabra": "corina"}, {"valor": 31, "palabra": "maduro"}, {"valor": 22, "palabra": "pueblo"}, {"valor": 21, "palabra": "venezuela"}, {"valor": 12, "palabra": "bendiga"}, {"valor": 11, "palabra": "machado"}, {"valor": 9, "palabra": "necesito"}, {"valor": 8, "palabra": "saludos"}, {"valor": 7, "palabra": "hambre"}, {"valor": 7, "palabra": "porque"}, {"valor": 6, "palabra": "crédito"}, {"valor": 6, "palabra": "estado"}, {"valor": 5, "palabra": "comandante"}, {"valor": 5, "palabra": "cuando"}, {"valor": 5, "palabra": "buenas"}, {"valor": 5, "palabra": "nuestra"}, {"valor": 5, "palabra": "elecciones"}, {"valor": 4, "palabra": "mentira"}, {"valor": 4, "palabra": "pasando"}, {"valor": 4, "palabra": "respuesta"}, {"valor": 4, "palabra": "tienes"}, {"valor": 4, "palabra": "jajajaja"}, {"valor": 4, "palabra": "nesecito"}, {"valor": 4, "palabra": "siempre"}, {"valor": 4, "palabra": "trabajar"}, {"valor": 4, "palabra": "memoria"}, {"valor": 4, "palabra": "bendiciones"}, {"valor": 4, "palabra": "gasolina"}, {"valor": 4, "palabra": "queremos"}, {"valor": 4, "palabra": "trabajo"}, {"valor": 3, "palabra": "chávez"}, {"valor": 3, "palabra": "personas"}, {"valor": 3, "palabra": "millones"}, {"valor": 3, "palabra": "crítica"}, {"valor": 3, "palabra": "camarada"}, {"valor": 3, "palabra": "verdad"}, {"valor": 3, "palabra": "nicolás"}, {"valor": 3, "palabra": "nuestro"}, {"valor": 3, "palabra": "municipio"}]}, "2024-03-11-2024-03-11": {"VEN - Medios adversos- TIK TOK": [{"valor": 12, "palabra": "nuestro"}, {"valor": 9, "palabra": "disponible"}, {"valor": 9, "palabra": "youtube"}, {"valor": 7, "palabra": "nuestra"}, {"valor": 7, "palabra": "venezuela"}, {"valor": 6, "palabra": "nuestras"}, {"valor": 6, "palabra": "sociales"}, {"valor": 6, "palabra": "impacto"}, {"valor": 5, "palabra": "noticias"}, {"valor": 5, "palabra": "destacadas"}, {"valor": 5, "palabra": "comunidad"}, {"valor": 5, "palabra": "síguenos"}, {"valor": 4, "palabra": "detalles"}, {"valor": 4, "palabra": "machado"}, {"valor": 3, "palabra": "pierdas"}, {"valor": 3, "palabra": "emisión"}, {"valor": 3, "palabra": "completa"}, {"valor": 3, "palabra": "noticiero"}, {"valor": 3, "palabra": "historias"}, {"valor": 3, "palabra": "ampliar"}, {"valor": 3, "palabra": "conoce"}, {"valor": 3, "palabra": "producción"}, {"valor": 3, "palabra": "thaitir"}, {"valor": 3, "palabra": "calderón"}, {"valor": 3, "palabra": "corina"}, {"valor": 2, "palabra": "maduro"}, {"valor": 2, "palabra": "oposición"}, {"valor": 2, "palabra": "olvides"}, {"valor": 2, "palabra": "comparte"}, {"valor": 2, "palabra": "fabiola"}, {"valor": 2, "palabra": "colmenarez"}, {"valor": 2, "palabra": "velasquez"}, {"valor": 2, "palabra": "página"}, {"valor": 2, "palabra": "candidatura"}, {"valor": 2, "palabra": "presidenciales"}, {"valor": 2, "palabra": "película"}, {"valor": 2, "palabra": "premios"}, {"valor": 2, "palabra": "visita"}, {"valor": 2, "palabra": "portal"}, {"valor": 1, "palabra": "libertad"}], "VEN - Medios afines - TIK TOK": [{"valor": 14, "palabra": "película"}, {"valor": 9, "palabra": "nuestro"}, {"valor": 7, "palabra": "pueblo"}, {"valor": 7, "palabra": "realidad"}, {"valor": 6, "palabra": "seguridad"}, {"valor": 6, "palabra": "nuestra"}, {"valor": 6, "palabra": "cuando"}, {"valor": 5, "palabra": "venezuela"}, {"valor": 5, "palabra": "maduro"}, {"valor": 5, "palabra": "robert"}, {"valor": 5, "palabra": "ironman"}, {"valor": 4, "palabra": "siempre"}, {"valor": 4, "palabra": "puedes"}, {"valor": 4, "palabra": "presidente"}, {"valor": 4, "palabra": "merece"}, {"valor": 3, "palabra": "bendiciones"}, {"valor": 3, "palabra": "nuestros"}, {"valor": 3, "palabra": "bienestar"}, {"valor": 3, "palabra": "primer"}, {"valor": 3, "palabra": "viernes"}, {"valor": 3, "palabra": "oppenheimer"}, {"valor": 3, "palabra": "ganador"}, {"valor": 3, "palabra": "alguien"}, {"valor": 3, "palabra": "grande"}, {"valor": 3, "palabra": "pelicula"}, {"valor": 3, "palabra": "ucrania"}, {"valor": 3, "palabra": "estaba"}, {"valor": 3, "palabra": "porque"}, {"valor": 2, "palabra": "servicio"}, {"valor": 2, "palabra": "territorial"}, {"valor": 2, "palabra": "oriente"}, {"valor": 2, "palabra": "maturín"}, {"valor": 2, "palabra": "alegría"}, {"valor": 2, "palabra": "ocamar"}, {"valor": 2, "palabra": "puerto"}, {"valor": 2, "palabra": "cabello"}, {"valor": 2, "palabra": "nuestras"}, {"valor": 2, "palabra": "recuerda"}, {"valor": 2, "palabra": "trabajamos"}, {"valor": 2, "palabra": "personas"}], "VEN - Nicolás Maduro - TIK TOK": [{"valor": 6, "palabra": "presidente"}, {"valor": 3, "palabra": "necesito"}, {"valor": 3, "palabra": "porfavor"}, {"valor": 2, "palabra": "hermosa"}, {"valor": 2, "palabra": "fuerza"}, {"valor": 2, "palabra": "pueblo"}, {"valor": 2, "palabra": "nuestra"}, {"valor": 2, "palabra": "bolivariana"}, {"valor": 2, "palabra": "corina"}, {"valor": 2, "palabra": "dejamos"}, {"valor": 2, "palabra": "estados"}, {"valor": 2, "palabra": "unidos"}, {"valor": 2, "palabra": "quiere"}, {"valor": 2, "palabra": "quiero"}, {"valor": 2, "palabra": "chávez"}, {"valor": 2, "palabra": "solucionar"}, {"valor": 2, "palabra": "maduro"}, {"valor": 2, "palabra": "ayudeme"}, {"valor": 1, "palabra": "sorpresa"}, {"valor": 1, "palabra": "motorizada"}, {"valor": 1, "palabra": "oriente"}, {"valor": 1, "palabra": "recibiéndome"}, {"valor": 1, "palabra": "maturín"}, {"valor": 1, "palabra": "alegría"}, {"valor": 1, "palabra": "bendiciones"}, {"valor": 1, "palabra": "cariño"}, {"valor": 1, "palabra": "ustedes"}, {"valor": 1, "palabra": "hermanas"}, {"valor": 1, "palabra": "hermanos"}, {"valor": 1, "palabra": "pasión"}, {"valor": 1, "palabra": "antiimperialista"}, {"valor": 1, "palabra": "espiritual"}, {"valor": 1, "palabra": "adelante"}, {"valor": 1, "palabra": "seguiremos"}, {"valor": 1, "palabra": "trabajando"}, {"valor": 1, "palabra": "intensamente"}, {"valor": 1, "palabra": "patria"}, {"valor": 1, "palabra": "revolución"}, {"valor": 1, "palabra": "transforma"}, {"valor": 1, "palabra": "bonitas"}]}}